garmin_fit_sdk/__init__.py
garmin_fit_sdk/accumulator.py
garmin_fit_sdk/bitstream.py
garmin_fit_sdk/crc_calculator.py
garmin_fit_sdk/decoder.py
garmin_fit_sdk/fit.py
garmin_fit_sdk/hr_mesg_utils.py
garmin_fit_sdk/profile.py
garmin_fit_sdk/stream.py
garmin_fit_sdk/util.py
tests/__init__.py
tests/data.py
tests/data_expand_hr_mesgs.py
tests/test_accumulator.py
tests/test_bitstream.py
tests/test_crc_calculator.py
tests/test_decoder.py
tests/test_hr_mesg_utils.py
tests/test_stream.py
tests/test_util.py
garmin_fit_sdk-21.188.0.dist-info/METADATA
garmin_fit_sdk-21.188.0.dist-info/WHEEL
garmin_fit_sdk-21.188.0.dist-info/top_level.txt
garmin_fit_sdk-21.188.0.dist-info/zip-safe
garmin_fit_sdk-21.188.0.dist-info/RECORD
